{
  "name": "border",
  "values": [
    {
      "name": "borderWidth",
      "values": []
    },
    {
      "name": "borderStyle",
      "values": []
    },
    {
      "name": "radii",
      "values": [
        {
          "name": "sm",
          "value": 3
        },
        {
          "name": "md",
          "value": 5
        },
        {
          "name": "lg",
          "value": 7
        },
        {
          "name": "pill",
          "value": 20
        },
        {
          "name": "circle",
          "value": "50%"
        }
      ]
    }
  ]
}